driftpy/__init__.py
driftpy/account_subscription_config.py
driftpy/accounts/__init__.py
driftpy/accounts/bulk_account_loader.py
driftpy/accounts/cache/__init__.py
driftpy/accounts/cache/drift_client.py
driftpy/accounts/cache/user.py
driftpy/accounts/demo/__init__.py
driftpy/accounts/demo/drift_client.py
driftpy/accounts/demo/user.py
driftpy/accounts/get_accounts.py
driftpy/accounts/grpc/account_subscriber.py
driftpy/accounts/grpc/drift_client.py
driftpy/accounts/grpc/geyser_codegen/README.md
driftpy/accounts/grpc/geyser_codegen/geyser_pb2.py
driftpy/accounts/grpc/geyser_codegen/geyser_pb2.pyi
driftpy/accounts/grpc/geyser_codegen/geyser_pb2_grpc.py
driftpy/accounts/grpc/geyser_codegen/solana_storage_pb2.py
driftpy/accounts/grpc/geyser_codegen/solana_storage_pb2.pyi
driftpy/accounts/grpc/geyser_codegen/solana_storage_pb2_grpc.py
driftpy/accounts/grpc/geyser_codegen/subscribe_geyser.py
driftpy/accounts/grpc/program_account_subscriber.py
driftpy/accounts/grpc/user.py
driftpy/accounts/grpc/user_stats.py
driftpy/accounts/oracle.py
driftpy/accounts/polling/__init__.py
driftpy/accounts/polling/drift_client.py
driftpy/accounts/polling/user.py
driftpy/accounts/types.py
driftpy/accounts/ws/__init__.py
driftpy/accounts/ws/account_subscriber.py
driftpy/accounts/ws/drift_client.py
driftpy/accounts/ws/multi_account_subscriber.py
driftpy/accounts/ws/program_account_subscriber.py
driftpy/accounts/ws/user.py
driftpy/accounts/ws/user_stats.py
driftpy/address_lookup_table.py
driftpy/addresses.py
driftpy/admin.py
driftpy/auction_subscriber/auction_subscriber.py
driftpy/auction_subscriber/grpc_auction_subscriber.py
driftpy/auction_subscriber/types.py
driftpy/constants/__init__.py
driftpy/constants/config.py
driftpy/constants/numeric_constants.py
driftpy/constants/perp_markets.py
driftpy/constants/spot_markets.py
driftpy/decode/pull_oracle.py
driftpy/decode/signed_msg_order.py
driftpy/decode/user.py
driftpy/decode/user_stat.py
driftpy/decode/utils.py
driftpy/dlob/client_types.py
driftpy-0.8.88.dist-info/METADATA
driftpy-0.8.88.dist-info/WHEEL
driftpy-0.8.88.dist-info/RECORD
