Metadata-Version: 2.1
Name: driftpy
Version: 0.8.88
Summary: A Python client for the Drift DEX
Home-page: https://github.com/drift-labs/driftpy
License: MIT
Author: x19
Author-email: https://twitter.com/0xNineteen@gmail.com
Requires-Python: >=3.10,<4.0
Classifier: License :: OSI Approved :: MIT License
Classifier: Programming Language :: Python :: 3
Classifier: Programming Language :: Python :: 3.10
Classifier: Programming Language :: Python :: 3.11
Requires-Dist: aiodns (==3.0.0)
Requires-Dist: aiohttp (>=3.9.1,<4.0.0)
Requires-Dist: aiosignal (==1.3.1)
Requires-Dist: anchorpy (==0.21.0)
Requires-Dist: anchorpy-core (==0.2.0)
Requires-Dist: anyio (==4.4.0)
Requires-Dist: apischema (==0.17.5)
Requires-Dist: async-timeout (>=4.0.2,<5.0.0)
Requires-Dist: attrs (==22.2.0)
Requires-Dist: backoff (==2.2.1)
Requires-Dist: base58 (==2.1.1)
Requires-Dist: based58 (==0.1.1)
Requires-Dist: borsh-construct (==0.1.0)
Requires-Dist: cachetools (==5.3)
Requires-Dist: certifi (==2025.1.31)
Requires-Dist: cffi (==1.17.1)
Requires-Dist: charset-normalizer (==2.1.1)
Requires-Dist: construct (==2.10.68)
Requires-Dist: construct-typing (==0.5.3)
Requires-Dist: deprecated (>=1.2.14,<2.0.0)
Requires-Dist: dnspython (==2.2.1)
Requires-Dist: events (>=0.5,<0.6)
Requires-Dist: exceptiongroup (==1.0.4)
Requires-Dist: grpcio (==1.68.1)
Requires-Dist: h11 (==0.14.0)
Requires-Dist: httpcore (==1.0.7)
Requires-Dist: httpx (==0.28.1)
Requires-Dist: idna (==3.4)
Requires-Dist: iniconfig (==1.1.1)
Requires-Dist: jsonalias (==0.1.1)
Requires-Dist: jsonrpcclient (==4.0.3)
Requires-Dist: jsonrpcserver (==5.0.9)
Requires-Dist: jsonschema (==4.18.0)
Requires-Dist: loguru (>=0.7.0,<0.8.0)
Requires-Dist: mccabe (==0.7.0)
Requires-Dist: more-itertools (==8.14.0)
Requires-Dist: numpy (>=1.26.2,<2.0.0)
Requires-Dist: oslash (==0.6.3)
Requires-Dist: packaging (==23.1)
Requires-Dist: protobuf (>=5.29.2,<6.0.0)
Requires-Dist: psutil (==5.9.4)
Requires-Dist: py (==1.11.0)
Requires-Dist: pycares (==4.3.0)
Requires-Dist: pycodestyle (==2.10.0)
Requires-Dist: pycparser (==2.21)
Requires-Dist: pyflakes (==3.0.1)
Requires-Dist: pyheck (==0.1.5)
Requires-Dist: pynacl (>=1.5.0,<2.0.0)
Requires-Dist: pyrsistent (==0.19.2)
Requires-Dist: pythclient (==0.2.1)
Requires-Dist: requests (>=2.28.1,<3.0.0)
Requires-Dist: rfc3986 (==1.5.0)
Requires-Dist: sniffio (==1.3.0)
Requires-Dist: solana (>=0.36,<0.37)
Requires-Dist: solders (>=0.23.0,<0.27.0)
Requires-Dist: sumtypes (==0.1a6)
Requires-Dist: toml (==0.10.2)
Requires-Dist: tomli (==2.0.1)
Requires-Dist: toolz (==0.11.2)
Requires-Dist: tqdm (>=4.67.1,<5.0.0)
Requires-Dist: types-cachetools (==4.2.10)
Requires-Dist: typing-extensions (>=4.4.0,<5.0.0)
Requires-Dist: urllib3 (==1.26.13)
Requires-Dist: websockets (==13.0)
Requires-Dist: yarl (>=1.9.4,<2.0.0)
Requires-Dist: zstandard (==0.18.0)
Project-URL: Documentation, https://drift-labs.github.io/driftpy/
